VisageSnap/__init__.py
VisageSnap/classes.py
VisageSnap/main.py
VisageSnap/utils.py
VisageSnap/image/__init__.py
VisageSnap/image/imageloader.py
VisageSnap/model/__init__.py
VisageSnap/model/modelhandler.py
VisageSnap/processor/__init__.py
VisageSnap/processor/faceprocessor.py
VisageSnap/processor/predictor.py
VisageSnap/processor/trainer.py
VisageSnap-0.3.2.dist-info/LICENSE
VisageSnap-0.3.2.dist-info/METADATA
VisageSnap-0.3.2.dist-info/WHEEL
VisageSnap-0.3.2.dist-info/top_level.txt
VisageSnap-0.3.2.dist-info/RECORD
