Metadata-Version: 2.1
Name: VisageSnap
Version: 0.3.2
Summary: Face Classification package
Home-page: https://github.com/asheswook/VisageSnap
Author: Jaewook Lee
Author-email: me@jwlee.xyz
Project-URL: Bug Tracker, https://github.com/asheswook/VisageSnap/issues
Classifier: Programming Language :: Python :: 3
Classifier: License :: OSI Approved :: MIT License
Classifier: Operating System :: OS Independent
Requires-Python: >=3.9
License-File: LICENSE
Requires-Dist: numpy
Requires-Dist: scikit-learn
Requires-Dist: dlib
Requires-Dist: face-recognition
